Dockerfile
MANIFEST.in
setup.py
version.py
larissa/Colorer.py
larissa/Factory.py
larissa/Project.py
larissa/__init__.py
larissa.egg-info/PKG-INFO
larissa.egg-info/SOURCES.txt
larissa.egg-info/dependency_links.txt
larissa.egg-info/requires.txt
larissa.egg-info/top_level.txt
larissa/Loader/ELF.py
larissa/Loader/Symbol.py
larissa/Loader/__init__.py
larissa/SimProcedures/__init__.py
larissa/SimProcedures/Syscalls/__init__.py
larissa/SimProcedures/Syscalls/SYSV/__init__.py
larissa/SimProcedures/Syscalls/SYSV/x64_64.py
larissa/SimProcedures/Syscalls/SYSV/x86_32.py
larissa/State/__init__.py
larissa/State/plugins/__init__.py
larissa/State/plugins/disasm.py
larissa/State/plugins/libc.py
larissa/State/plugins/memory.py
larissa/State/plugins/posix.py
larissa/State/plugins/regs.py
larissa/State/plugins/se.py
larissa/State/plugins/SolverEngine/Byte.py
larissa/State/plugins/SolverEngine/Bytes.py
larissa/State/plugins/SolverEngine/__init__.py
lib/triton/.appveyor.yml
lib/triton/.build_number
lib/triton/.codecov.yml
lib/triton/.git
lib/triton/.gitignore
lib/triton/.travis.yml
lib/triton/CMakeLists.txt
lib/triton/Dockerfile
lib/triton/LICENSE_BSD.txt
lib/triton/README.md
lib/triton/CMakeModules/FindCAPSTONE.cmake
lib/triton/CMakeModules/FindZ3.cmake
lib/triton/CMakeModules/LibFindMacros.cmake
lib/triton/doc/CMakeLists.txt
lib/triton/doc/Doxyfile.in
lib/triton/doc/extract_doc.py
lib/triton/src/CMakeLists.txt
lib/triton/src/examples/CMakeLists.txt
lib/triton/src/examples/cpp/CMakeLists.txt
lib/triton/src/examples/cpp/Makefile
lib/triton/src/examples/cpp/constraint.cpp
lib/triton/src/examples/cpp/info_reg.cpp
lib/triton/src/examples/cpp/ir.cpp
lib/triton/src/examples/cpp/simplification.cpp
lib/triton/src/examples/cpp/taint_reg.cpp
lib/triton/src/examples/pin/ast_dictionaries.py
lib/triton/src/examples/pin/blacklist.py
lib/triton/src/examples/pin/callback_concrete_needs.py
lib/triton/src/examples/pin/callback_image.py
lib/triton/src/examples/pin/callback_routine.py
lib/triton/src/examples/pin/callback_signals.py
lib/triton/src/examples/pin/callback_syscall.py
lib/triton/src/examples/pin/count_inst.py
