Metadata-Version: 1.1
Name: larissa
Version: 0.0.10
Summary: Tool to automate working with Triton
Home-page: https://github.com/owlz/larissa
Author: Michael Bann
Author-email: self@bannsecurity.com
License: MIT
Keywords: symbolic execution triton
Platform: UNKNOWN
Classifier: Development Status :: 3 - Alpha
Classifier: Intended Audience :: End Users/Desktop
Classifier: License :: OSI Approved :: MIT License
Classifier: Programming Language :: Python :: 2
Classifier: Operating System :: POSIX :: Linux
Classifier: Environment :: Console
